pgh.py
PGH-0.1.dist-info/DESCRIPTION.rst
PGH-0.1.dist-info/METADATA
PGH-0.1.dist-info/RECORD
PGH-0.1.dist-info/WHEEL
PGH-0.1.dist-info/entry_points.txt
PGH-0.1.dist-info/metadata.json
PGH-0.1.dist-info/top_level.txt
