Metadata-Version: 2.0
Name: PGH
Version: 0.1
Summary: PGH is a command line tool to help you monitor and debug your PostgreSQL database.
Home-page: https://github.com/nata79/pgh
Author: André Barbosa
Author-email: albmail88@gmail.com
License: MIT
Keywords: pg postgres postgresql
Platform: UNKNOWN
Requires-Dist: click
Requires-Dist: psycopg2
Requires-Dist: tabulate
